h2ogpt/__init__.py
h2ogpt/generate.py
h2ogpt/gradio_utils/__init__.py
h2ogpt/gradio_utils/css.py
h2ogpt/gradio_utils/google_auth.py
h2ogpt/gradio_utils/grclient.py
h2ogpt/gradio_utils/prompt_form.py
h2ogpt/iterators/__init__.py
h2ogpt/iterators/iterator_pipe.py
h2ogpt/iterators/timeout_iterator.py
h2ogpt/metrics/__init__.py
h2ogpt/metrics/quip.py
h2ogpt/models/__init__.py
h2ogpt/models/create_model_cards.py
h2ogpt/models/gpu_mem_track.py
h2ogpt/models/predict_aquila.py
h2ogpt/models/test_scrape1.py
h2ogpt/openai_server/__init__.py
h2ogpt/openai_server/backend.py
h2ogpt/openai_server/backend_utils.py
h2ogpt/openai_server/function_server.py
h2ogpt/openai_server/log.py
h2ogpt/openai_server/server.py
h2ogpt/openai_server/server_start.py
h2ogpt/openai_server/test_conversion.py
h2ogpt/openai_server/test_openai_server.py
h2ogpt/spkemb/cmu_us_awb_arctic-wav-arctic_a0002.npy
h2ogpt/spkemb/cmu_us_bdl_arctic-wav-arctic_a0009.npy
h2ogpt/spkemb/cmu_us_clb_arctic-wav-arctic_a0144.npy
h2ogpt/spkemb/cmu_us_ksp_arctic-wav-arctic_b0087.npy
h2ogpt/spkemb/cmu_us_rms_arctic-wav-arctic_b0353.npy
h2ogpt/spkemb/cmu_us_slt_arctic-wav-arctic_a0508.npy
h2ogpt/src/__init__.py
h2ogpt/src/audio_langchain.py
h2ogpt/src/basic_nltk.py
h2ogpt/src/cli.py
h2ogpt/src/client_test.py
h2ogpt/src/create_data.py
h2ogpt/src/db_utils.py
h2ogpt/src/enums.py
h2ogpt/src/eval.py
h2ogpt/src/evaluate_params.py
h2ogpt/src/export_hf_checkpoint.py
h2ogpt/src/function_client.py
h2ogpt/src/function_server.py
h2ogpt/src/gen.py
h2ogpt/src/gpt4all_llm.py
h2ogpt/src/gpt_langchain.py
h2ogpt/src/gradio_funcs.py
h2ogpt/src/gradio_runner.py
h2ogpt/src/gradio_themes.py
h2ogpt/src/h2oai_pipeline.py
h2ogpt/src/image_captions.py
h2ogpt/src/image_doctr.py
h2ogpt/src/image_pix2struct.py
h2ogpt/src/image_utils.py
h2ogpt/src/llama_flash_attn_monkey_patch.py
h2ogpt/src/llm_exllama.py
h2ogpt/src/loaders.py
h2ogpt/src/make_db.py
h2ogpt/src/output_parser.py
h2ogpt/src/pandas_agent_langchain.py
h2ogpt/src/prepare_offline.py
h2ogpt-0.2.1.dist-info/LICENSE
h2ogpt-0.2.1.dist-info/METADATA
h2ogpt-0.2.1.dist-info/WHEEL
h2ogpt-0.2.1.dist-info/entry_points.txt
h2ogpt-0.2.1.dist-info/top_level.txt
h2ogpt-0.2.1.dist-info/RECORD
