Metadata-Version: 2.1
Name: h2ogpt
Version: 0.2.1
Home-page: https://github.com/h2oai/h2ogpt
Download-URL: 
Author: H2O.ai
Author-email: jon.mckinney@h2o.ai, arno@h2o.ai
License: https://opensource.org/license/apache-2-0/
Keywords: LLM,AI
Requires-Python: >=3.10
License-File: LICENSE
Requires-Dist: uvicorn[standard]
Requires-Dist: gunicorn
Requires-Dist: fastapi-utils
Requires-Dist: sse-starlette ==1.8.2
Requires-Dist: huggingface-hub >=0.12.4
Requires-Dist: appdirs ==1.4.4
Requires-Dist: fire ==0.5.0
Requires-Dist: docutils ==0.20.1
Requires-Dist: evaluate ==0.4.0
Requires-Dist: rouge-score ==0.1.2
Requires-Dist: sacrebleu ==2.3.1
Requires-Dist: scikit-learn >=1.2.2
Requires-Dist: numpy <2.0,>=1.23.4
Requires-Dist: pandas >=2.0.2
Requires-Dist: matplotlib >=3.7.1
Requires-Dist: loralib >=0.1.2
Requires-Dist: bitsandbytes >=0.43.1
Requires-Dist: accelerate >=0.30.1
Requires-Dist: peft >=0.7.0
Requires-Dist: transformers >=4.41.0
Requires-Dist: tokenizers >=0.19.0
Requires-Dist: hf-transfer >=0.1.6
Requires-Dist: optimum >=1.17.1
Requires-Dist: datasets >=2.18.0
Requires-Dist: sentencepiece >=0.2.0
Requires-Dist: APScheduler >=3.10.1
Requires-Dist: pynvml >=11.5.0
Requires-Dist: psutil >=5.9.5
Requires-Dist: boto3 >=1.26.101
Requires-Dist: botocore >=1.29.101
Requires-Dist: beautifulsoup4 >=4.12.2
Requires-Dist: markdown >=3.4.3
Requires-Dist: pytest >=7.2.2
Requires-Dist: pytest-xdist >=3.2.1
Requires-Dist: nltk >=3.8.1
Requires-Dist: textstat >=0.7.3
Requires-Dist: openpyxl >=3.1.2
Requires-Dist: lm-dataformat >=0.0.20
Requires-Dist: bioc >=2.0
Requires-Dist: einops >=0.6.1
Requires-Dist: instructorembedding >=1.0.1
Requires-Dist: python-dotenv >=1.0.0
Requires-Dist: json-repair >=0.21.0
Requires-Dist: text-generation >=0.7.0
Requires-Dist: tiktoken >=0.5.2
Requires-Dist: openai >=1.27.0
Requires-Dist: requests >=2.31.0
Requires-Dist: httpx >=0.24.1
Requires-Dist: urllib3 >=1.26.16
Requires-Dist: filelock >=3.12.2
Requires-Dist: joblib >=1.3.1
Requires-Dist: tqdm >=4.65.0
Requires-Dist: tabulate >=0.9.0
Requires-Dist: packaging >=23.1
Requires-Dist: langchain ==0.1.19
Requires-Dist: langchain-experimental ==0.0.58
Requires-Dist: langchain-community ==0.0.38
Requires-Dist: langsmith ==0.1.56
Requires-Dist: langchain-core ==0.1.52
Requires-Dist: langchain-text-splitters ==0.0.1
Requires-Dist: pypdf >=3.17.1
Requires-Dist: pypdfium2 >=4.24.0
Requires-Dist: sentence-transformers <2.3.0,>=2.2.2
Requires-Dist: replicate ==0.25.2
Requires-Dist: anthropic ==0.25.8
Requires-Dist: langchain-anthropic >=0.1.6
Requires-Dist: together ==1.1.5
Requires-Dist: langchain-together ==0.1.1
Requires-Dist: langchain-openai ==0.1.6
Requires-Dist: langchain-google-genai ==1.0.3
Requires-Dist: google-generativeai ==0.5.2
Requires-Dist: httpx >=0.25.2
Requires-Dist: httpx-sse >=0.3.1
Requires-Dist: mistralai ==0.3.0
Requires-Dist: groq ==0.5.0
Requires-Dist: langchain-groq ==0.1.3
Requires-Dist: chromadb ==0.4.23
Requires-Dist: pydantic-settings >=2.1.0
Requires-Dist: unstructured[local-inference] ==0.12.5
Requires-Dist: unstructured[all-docs] ==0.12.5
Requires-Dist: docx2txt ==0.8
Requires-Dist: python-docx ==1.1.0
Requires-Dist: pillow >=10.2.0
Requires-Dist: posthog
Requires-Dist: pdfminer.six ==20231228
Requires-Dist: urllib3
Requires-Dist: requests-file
Requires-Dist: pip-licenses >=4.3.0
Requires-Dist: weaviate-client ==3.26.2
Requires-Dist: gradio-pdf >=0.0.7
Requires-Dist: gradio-tools >=0.0.9
Requires-Dist: qdrant-client >=1.8.0
Requires-Dist: certifi >=2023.7.22
Requires-Dist: fastapi >=0.109.1
Requires-Dist: numpy >=1.22.2
Requires-Dist: setuptools >=65.5.1
Requires-Dist: sympy >=1.12
Requires-Dist: wheel >=0.38.0
Requires-Dist: gpt4all ==1.0.5
Requires-Dist: llama-cpp-python ==0.2.76
Requires-Dist: arxiv ==1.4.8
Requires-Dist: pymupdf >=1.23.8
Requires-Dist: google-search-results >=2.4.2
Requires-Dist: duckduckgo-search >=4.1.1
Requires-Dist: wikipedia >=1.4.0
Requires-Dist: wolframalpha >=5.0.0
Requires-Dist: semanticscholar >=0.7.0
Requires-Dist: playwright >=1.37.0
Requires-Dist: selenium >=4.11.2
Requires-Dist: html2text >=2020.1.16
Requires-Dist: bs4 >=0.0.1
Requires-Dist: weasyprint >=60.1
Requires-Dist: imutils >=0.5.4
Requires-Dist: opencv-python-headless >=4.8.1.78
Requires-Dist: pydub >=0.25.1
Requires-Dist: librosa >=0.10.1
Requires-Dist: ffmpeg >=1.4
Requires-Dist: yt-dlp >=2024.3.10
Requires-Dist: wavio >=0.0.8
Requires-Dist: soundfile ==0.12.1
Requires-Dist: torchaudio
Requires-Dist: soundfile >=0.12.1
Requires-Dist: noisereduce
Requires-Dist: emoji
Requires-Dist: ffmpeg-python
Requires-Dist: trainer
Requires-Dist: pysbd
Requires-Dist: coqpit
Requires-Dist: cutlet >=0.3.0
Requires-Dist: langid >=1.1.6
Requires-Dist: g2pkk >=0.1.2
Requires-Dist: jamo >=0.4.1
Requires-Dist: gruut[de,es,fr] >=2.2.3
Requires-Dist: jieba >=0.42.1
Requires-Dist: fiftyone >=0.23.8
Requires-Dist: pytube
Requires-Dist: diffusers ==0.24.0
Requires-Dist: yt-dlp >=2024.5.27
Requires-Dist: pypandoc-binary >=1.11 ; platform_machine == "x86_64"
Requires-Dist: jq >=1.4.1 ; platform_machine == "x86_64"
Requires-Dist: pypandoc-binary >=1.11 ; platform_system == "Windows"
Requires-Dist: python-magic-bin >=0.4.14 ; platform_system == "Windows"
Requires-Dist: torch ==2.2.1 ; sys_platform != "darwin" and platform_machine != "arm64"
Requires-Dist: torch ==2.2.1 ; sys_platform == "darwin" and platform_machine == "arm64"
Requires-Dist: pypandoc >=1.11 ; sys_platform == "darwin" and platform_machine == "arm64"
Provides-Extra: training
Requires-Dist: tensorboard >=2.13.0 ; extra == 'training'
Requires-Dist: neptune >=1.2.0 ; extra == 'training'
Provides-Extra: wiki_extra
Requires-Dist: mwxml >=0.3.3 ; extra == 'wiki_extra'
Requires-Dist: mwparserfromhell >=0.6.4 ; extra == 'wiki_extra'
Provides-Extra: cpu
Requires-Dist: faiss-cpu >=1.7.4 ; extra == 'cpu'
Requires-Dist: onnxruntime ==1.15.0 ; extra == 'cpu'
Provides-Extra: cuda
Requires-Dist: faiss-gpu >=1.7.2 ; extra == 'cuda'
Requires-Dist: onnxruntime-gpu ==1.15.0 ; extra == 'cuda'
Requires-Dist: auto-gptq >=0.7.1 ; extra == 'cuda'
Requires-Dist: optimum >=1.17.1 ; extra == 'cuda'
Requires-Dist: autoawq ; extra == 'cuda'
Requires-Dist: autoawq-kernels ; extra == 'cuda'
Provides-Extra: local-inference
Requires-Dist: unstructured[local-inference] <0.13,>=0.12.5 ; extra == 'local-inference'
